autotranscribe/__init__.py
autotranscribe/advanced.py
autotranscribe/splitter.py
autotranscribe/transcribe_cli.py
autotranscribe/transcriber.py
autotranscribe/videoproc.py
autotranscribe-0.1.5.dist-info/LICENSE
autotranscribe-0.1.5.dist-info/METADATA
autotranscribe-0.1.5.dist-info/WHEEL
autotranscribe-0.1.5.dist-info/RECORD
